[
    {
        "default_validation_metric": "nDCGRendle2020",
        "default_validation_cutoff": 10,
        "rel_threshold": 0
    },
    {
        "meta": {},
        "recommender": "UMAP@128",
        "configuration": {
            "folder": "C:\\Users\\zanzo\\Documents\\GitHub\\AIML-LIGHT_GCN\\data_dz\\yahoo_movies\\UMAP",
            "path": "C:\\Users\\zanzo\\Documents\\GitHub\\AIML-LIGHT_GCN\\data_dz\\yahoo_movies\\UMAP\\UMAP@128.tsv",
            "name": "UMAP@128"
        }
    },
    {
        "meta": {},
        "recommender": "UMAP@16",
        "configuration": {
            "folder": "C:\\Users\\zanzo\\Documents\\GitHub\\AIML-LIGHT_GCN\\data_dz\\yahoo_movies\\UMAP",
            "path": "C:\\Users\\zanzo\\Documents\\GitHub\\AIML-LIGHT_GCN\\data_dz\\yahoo_movies\\UMAP\\UMAP@16.tsv",
            "name": "UMAP@16"
        }
    },
    {
        "meta": {},
        "recommender": "UMAP@2",
        "configuration": {
            "folder": "C:\\Users\\zanzo\\Documents\\GitHub\\AIML-LIGHT_GCN\\data_dz\\yahoo_movies\\UMAP",
            "path": "C:\\Users\\zanzo\\Documents\\GitHub\\AIML-LIGHT_GCN\\data_dz\\yahoo_movies\\UMAP\\UMAP@2.tsv",
            "name": "UMAP@2"
        }
    },
    {
        "meta": {},
        "recommender": "UMAP@32",
        "configuration": {
            "folder": "C:\\Users\\zanzo\\Documents\\GitHub\\AIML-LIGHT_GCN\\data_dz\\yahoo_movies\\UMAP",
            "path": "C:\\Users\\zanzo\\Documents\\GitHub\\AIML-LIGHT_GCN\\data_dz\\yahoo_movies\\UMAP\\UMAP@32.tsv",
            "name": "UMAP@32"
        }
    },
    {
        "meta": {},
        "recommender": "UMAP@4",
        "configuration": {
            "folder": "C:\\Users\\zanzo\\Documents\\GitHub\\AIML-LIGHT_GCN\\data_dz\\yahoo_movies\\UMAP",
            "path": "C:\\Users\\zanzo\\Documents\\GitHub\\AIML-LIGHT_GCN\\data_dz\\yahoo_movies\\UMAP\\UMAP@4.tsv",
            "name": "UMAP@4"
        }
    },
    {
        "meta": {},
        "recommender": "UMAP@64",
        "configuration": {
            "folder": "C:\\Users\\zanzo\\Documents\\GitHub\\AIML-LIGHT_GCN\\data_dz\\yahoo_movies\\UMAP",
            "path": "C:\\Users\\zanzo\\Documents\\GitHub\\AIML-LIGHT_GCN\\data_dz\\yahoo_movies\\UMAP\\UMAP@64.tsv",
            "name": "UMAP@64"
        }
    },
    {
        "meta": {},
        "recommender": "UMAP@8",
        "configuration": {
            "folder": "C:\\Users\\zanzo\\Documents\\GitHub\\AIML-LIGHT_GCN\\data_dz\\yahoo_movies\\UMAP",
            "path": "C:\\Users\\zanzo\\Documents\\GitHub\\AIML-LIGHT_GCN\\data_dz\\yahoo_movies\\UMAP\\UMAP@8.tsv",
            "name": "UMAP@8"
        }
    }
]